matrix_io_proto-0.0.32-py3.6-nspkg.pth
matrix_io/proto/__init__.py
matrix_io/proto/common/__init__.py
matrix_io/proto/common/entity_pb2.py
matrix_io/proto/common/entity_pb2_grpc.py
matrix_io/proto/malos/__init__.py
matrix_io/proto/malos/v1/__init__.py
matrix_io/proto/malos/v1/comm_pb2.py
matrix_io/proto/malos/v1/comm_pb2_grpc.py
matrix_io/proto/malos/v1/driver_pb2.py
matrix_io/proto/malos/v1/driver_pb2_grpc.py
matrix_io/proto/malos/v1/io_pb2.py
matrix_io/proto/malos/v1/io_pb2_grpc.py
matrix_io/proto/malos/v1/maloseye_pb2.py
matrix_io/proto/malos/v1/maloseye_pb2_grpc.py
matrix_io/proto/malos/v1/sense_pb2.py
matrix_io/proto/malos/v1/sense_pb2_grpc.py
matrix_io/proto/malos/v1/zwave_commands_pb2.py
matrix_io/proto/malos/v1/zwave_commands_pb2_grpc.py
matrix_io/proto/recognition/__init__.py
matrix_io/proto/recognition/v1/__init__.py
matrix_io/proto/recognition/v1/recognition_pb2.py
matrix_io/proto/recognition/v1/recognition_pb2_grpc.py
matrix_io/proto/recognition/v1/recognition_service_pb2.py
matrix_io/proto/recognition/v1/recognition_service_pb2_grpc.py
matrix_io/proto/vision/__init__.py
matrix_io/proto/vision/v1/__init__.py
matrix_io/proto/vision/v1/vision_pb2.py
matrix_io/proto/vision/v1/vision_pb2_grpc.py
matrix_io/proto/vision/v1/vision_service_pb2.py
matrix_io/proto/vision/v1/vision_service_pb2_grpc.py
matrix_io_proto-0.0.32.dist-info/METADATA
matrix_io_proto-0.0.32.dist-info/WHEEL
matrix_io_proto-0.0.32.dist-info/namespace_packages.txt
matrix_io_proto-0.0.32.dist-info/top_level.txt
matrix_io_proto-0.0.32.dist-info/RECORD
