Metadata-Version: 2.1
Name: matrix-io-proto
Version: 0.0.32
Summary: Protobufs used MATRIX ecosystem
Home-page: https://github.com/matrix-io/protocol-buffers
Author: MATRIX Labs
Author-email: devel@matrixlabs.ai
License: GPLv3
Platform: UNKNOWN
Classifier: Development Status :: 4 - Beta
Classifier: Intended Audience :: Developers
Classifier: License :: OSI Approved :: GNU General Public License v3 (GPLv3)
Classifier: Programming Language :: Python
Classifier: Programming Language :: Python :: 2
Classifier: Programming Language :: Python :: 2.7
Classifier: Programming Language :: Python :: 3
Classifier: Programming Language :: Python :: 3.4
Classifier: Programming Language :: Python :: 3.5
Classifier: Programming Language :: Python :: 3.6
Requires-Dist: protobuf (>=3.6.0)
Provides-Extra: grpc
Requires-Dist: grpcio (>=1.12.0) ; extra == 'grpc'
